docowling/__init__.py
docowling/backend/__init__.py
docowling/backend/abstract_backend.py
docowling/backend/asciidoc_backend.py
docowling/backend/csv_backend.py
docowling/backend/docling_parse_backend.py
docowling/backend/docling_parse_v2_backend.py
docowling/backend/html_backend.py
docowling/backend/md_backend.py
docowling/backend/msexcel_backend.py
docowling/backend/mspowerpoint_backend.py
docowling/backend/msword_backend.py
docowling/backend/pdf_backend.py
docowling/backend/pypdfium2_backend.py
docowling/backend/xml/__init__.py
docowling/backend/xml/pubmed_backend.py
docowling/backend/xml/uspto_backend.py
docowling/chunking/__init__.py
docowling/cli/__init__.py
docowling/cli/main.py
docowling/datamodel/__init__.py
docowling/datamodel/base_models.py
docowling/datamodel/document.py
docowling/datamodel/pipeline_options.py
docowling/datamodel/settings.py
docowling/document_converter.py
docowling/exceptions.py
docowling/models/__init__.py
docowling/models/base_model.py
docowling/models/base_ocr_model.py
docowling/models/ds_glm_model.py
docowling/models/easyocr_model.py
docowling/models/layout_model.py
docowling/models/ocr_mac_model.py
docowling/models/page_assemble_model.py
docowling/models/page_preprocessing_model.py
docowling/models/rapid_ocr_model.py
docowling/models/table_structure_model.py
docowling/models/tesseract_ocr_cli_model.py
docowling/models/tesseract_ocr_model.py
docowling/pipeline/__init__.py
docowling/pipeline/base_pipeline.py
docowling/pipeline/simple_pipeline.py
docowling/pipeline/standard_pdf_pipeline.py
docowling/py.typed
docowling/utils/__init__.py
docowling/utils/accelerator_utils.py
docowling/utils/export.py
docowling/utils/glm_utils.py
docowling/utils/layout_postprocessor.py
docowling/utils/profiling.py
docowling/utils/utils.py
docowling-1.0.17.dist-info/entry_points.txt
docowling-1.0.17.dist-info/LICENSE
docowling-1.0.17.dist-info/METADATA
docowling-1.0.17.dist-info/WHEEL
docowling-1.0.17.dist-info/RECORD
