Metadata-Version: 2.1
Name: docowling
Version: 1.0.17
Summary: SDK and CLI for parsing PDF, DOCX, HTML, and more, to a unified document representation for powering downstream workflows such as gen AI applications.
Home-page: https://github.com/mouraworks/docowling
License: MIT
Keywords: docowling,convert,document,pdf,docx,html,markdown,layout model,segmentation,table structure,table former
Author: Christoph Auer
Author-email: cau@zurich.ibm.com
Requires-Python: >=3.9,<4.0
Classifier: Development Status :: 5 - Production/Stable
Classifier: Intended Audience :: Developers
Classifier: Intended Audience :: Science/Research
Classifier: License :: OSI Approved :: MIT License
Classifier: Operating System :: MacOS :: MacOS X
Classifier: Operating System :: POSIX :: Linux
Classifier: Programming Language :: Python :: 3
Classifier: Programming Language :: Python :: 3.9
Classifier: Programming Language :: Python :: 3.10
Classifier: Programming Language :: Python :: 3.11
Classifier: Programming Language :: Python :: 3.12
Classifier: Programming Language :: Python :: 3.13
Classifier: Topic :: Scientific/Engineering :: Artificial Intelligence
Provides-Extra: ocrmac
Provides-Extra: rapidocr
Provides-Extra: tesserocr
Requires-Dist: beautifulsoup4 (>=4.12.3,<5.0.0)
Requires-Dist: certifi (>=2024.7.4)
Requires-Dist: chardet (>=5.2.0,<6.0.0)
Requires-Dist: deepsearch-glm (>=1.0.0,<2.0.0)
Requires-Dist: docling-core[chunking] (>=2.12.1,<3.0.0)
Requires-Dist: docling-ibm-models (>=3.1.0,<4.0.0)
Requires-Dist: docling-parse (>=3.0.0,<4.0.0)
Requires-Dist: easyocr (>=1.7,<2.0)
Requires-Dist: filetype (>=1.2.0,<2.0.0)
Requires-Dist: huggingface_hub (>=0.23,<1)
Requires-Dist: lxml (>=4.0.0,<6.0.0)
Requires-Dist: marko (>=2.1.2,<3.0.0)
Requires-Dist: ocrmac (>=1.0.0,<2.0.0) ; (sys_platform == "darwin") and (extra == "ocrmac")
Requires-Dist: onnxruntime (>=1.7.0,<1.20.0) ; (python_version < "3.10") and (extra == "rapidocr")
Requires-Dist: onnxruntime (>=1.7.0,<2.0.0) ; (python_version >= "3.10") and (extra == "rapidocr")
Requires-Dist: openpyxl (>=3.1.5,<4.0.0)
Requires-Dist: pandas (>=2.1.4,<3.0.0)
Requires-Dist: pydantic (>=2.0.0,<3.0.0)
Requires-Dist: pydantic-settings (>=2.3.0,<3.0.0)
Requires-Dist: pypdfium2 (>=4.30.0,<5.0.0)
Requires-Dist: python-docx (>=1.1.2,<2.0.0)
Requires-Dist: python-pptx (>=1.0.2,<2.0.0)
Requires-Dist: rapidocr-onnxruntime (>=1.4.0,<2.0.0) ; (python_version < "3.13") and (extra == "rapidocr")
Requires-Dist: requests (>=2.32.3,<3.0.0)
Requires-Dist: rtree (>=1.3.0,<2.0.0)
Requires-Dist: scipy (>=1.6.0,<2.0.0)
Requires-Dist: tesserocr (>=2.7.1,<3.0.0) ; extra == "tesserocr"
Requires-Dist: typer (>=0.12.5,<0.13.0)
Project-URL: Repository, https://github.com/mouraworks/docowling
